{
  "slug": "hayashi-akira-ta",
  "name": "林 晃汰",
  "nameRomaji": "Hayashi Akira Ta",
  "teamAbbr": "広",
  "teamSlug": "hiroshima-carp",
  "teamName": "広島東洋カープ",
  "league": "central",
  "group": "batting",
  "qualified": false,
  "season": "2026",
  "rank": null,
  "stats": {
    "avg": 0.0,
    "games": 8,
    "pa": 13,
    "ab": 11,
    "runs": 0,
    "hits": 0,
    "doubles": 0,
    "triples": 0,
    "hr": 0,
    "tb": 0,
    "rbi": 0,
    "sb": 0,
    "cs": 0,
    "sac": 0,
    "sf": 0,
    "bb": 2,
    "ibb": 0,
    "hbp": 0,
    "so": 3,
    "gidp": 1,
    "slg": 0.0,
    "obp": 0.154,
    "ops": 0.154
  },
  "asOf": "2026-07-03",
  "fetchedAt": "2026-07-04T17:57:51Z",
  "source": "NPB.jp 日本野球機構",
  "sourceUrl": "https://npb.jp/bis/2026/stats/idb1_c.html"
}