{
  "slug": "hideto-asamura",
  "name": "浅村 栄斗",
  "nameRomaji": "Hideto Asamura",
  "teamAbbr": "楽",
  "teamSlug": "rakuten-eagles",
  "teamName": "東北楽天ゴールデンイーグルス",
  "league": "pacific",
  "group": "batting",
  "qualified": true,
  "season": "2026",
  "rank": 16,
  "stats": {
    "avg": 0.251,
    "games": 52,
    "pa": 196,
    "ab": 171,
    "runs": 16,
    "hits": 43,
    "doubles": 5,
    "triples": 0,
    "hr": 5,
    "tb": 63,
    "rbi": 20,
    "sb": 1,
    "cs": 0,
    "sac": 0,
    "sf": 2,
    "bb": 21,
    "ibb": 1,
    "hbp": 2,
    "so": 38,
    "gidp": 6,
    "slg": 0.368,
    "obp": 0.337,
    "ops": 0.705
  },
  "asOf": "2026-06-08",
  "fetchedAt": "2026-06-08T18:24:37Z",
  "source": "NPB.jp 日本野球機構",
  "sourceUrl": "https://npb.jp/bis/2026/stats/bat_p.html"
}