{
  "slug": "hirooka-taishi",
  "name": "廣岡 大志",
  "nameRomaji": "Hirooka Taishi",
  "teamAbbr": "オ",
  "teamSlug": "orix-buffaloes",
  "teamName": "オリックス・バファローズ",
  "league": "pacific",
  "group": "batting",
  "qualified": false,
  "season": "2026",
  "rank": null,
  "stats": {
    "avg": 0.191,
    "games": 13,
    "pa": 51,
    "ab": 47,
    "runs": 5,
    "hits": 9,
    "doubles": 0,
    "triples": 0,
    "hr": 0,
    "tb": 9,
    "rbi": 3,
    "sb": 0,
    "cs": 1,
    "sac": 0,
    "sf": 1,
    "bb": 3,
    "ibb": 0,
    "hbp": 0,
    "so": 16,
    "gidp": 4,
    "slg": 0.191,
    "obp": 0.235,
    "ops": 0.426
  },
  "asOf": "2026-07-12",
  "fetchedAt": "2026-07-13T16:21:32Z",
  "source": "NPB.jp 日本野球機構",
  "sourceUrl": "https://npb.jp/bis/2026/stats/idb1_b.html"
}