{
  "slug": "inoue-on-dai",
  "name": "井上 温大",
  "nameRomaji": "Inoue On Dai",
  "teamAbbr": "巨",
  "teamSlug": "yomiuri-giants",
  "teamName": "読売ジャイアンツ",
  "league": "central",
  "group": "pitching",
  "qualified": true,
  "season": "2026",
  "rank": 5,
  "stats": {
    "era": 2.17,
    "games": 14,
    "wins": 8,
    "losses": 5,
    "saves": 0,
    "holds": 0,
    "hp": 0,
    "cg": 1,
    "sho": 0,
    "nbb": 1,
    "winpct": 0.615,
    "bf": 340,
    "ip": 87,
    "hits": 65,
    "hr": 5,
    "bb": 20,
    "ibb": 1,
    "hbp": 1,
    "so": 87,
    "wp": 1,
    "balk": 0,
    "runs": 25,
    "er": 21,
    "whip": 0.98
  },
  "asOf": "2026-07-16",
  "fetchedAt": "2026-07-17T03:53:29Z",
  "source": "NPB.jp 日本野球機構",
  "sourceUrl": "https://npb.jp/bis/2026/stats/pit_c.html"
}