{
  "slug": "keita-nakagawa",
  "name": "中川 圭太",
  "nameRomaji": "Keita Nakagawa",
  "teamAbbr": "オ",
  "teamSlug": "orix-buffaloes",
  "teamName": "オリックス・バファローズ",
  "league": "pacific",
  "group": "batting",
  "qualified": true,
  "season": "2026",
  "rank": 14,
  "stats": {
    "avg": 0.273,
    "games": 54,
    "pa": 214,
    "ab": 194,
    "runs": 28,
    "hits": 53,
    "doubles": 10,
    "triples": 1,
    "hr": 4,
    "tb": 77,
    "rbi": 23,
    "sb": 2,
    "cs": 2,
    "sac": 0,
    "sf": 3,
    "bb": 15,
    "ibb": 0,
    "hbp": 2,
    "so": 22,
    "gidp": 1,
    "slg": 0.397,
    "obp": 0.327,
    "ops": 0.724
  },
  "asOf": "2026-06-11",
  "fetchedAt": "2026-06-11T18:45:41Z",
  "source": "NPB.jp 日本野球機構",
  "sourceUrl": "https://npb.jp/bis/2026/stats/bat_p.html"
}