{
  "slug": "kihada",
  "name": "キハダ",
  "nameRomaji": "Kihada",
  "teamAbbr": "ヤ",
  "teamSlug": "yakult-swallows",
  "teamName": "東京ヤクルトスワローズ",
  "league": "central",
  "group": "pitching",
  "qualified": false,
  "season": "2026",
  "rank": 2,
  "stats": {
    "era": 2.36,
    "games": 28,
    "wins": 2,
    "losses": 3,
    "saves": 18,
    "holds": 1,
    "hp": 3,
    "cg": 0,
    "sho": 0,
    "nbb": 0,
    "winpct": 0.4,
    "bf": 119,
    "ip": 26.2,
    "hits": 18,
    "hr": 1,
    "bb": 16,
    "ibb": 0,
    "hbp": 3,
    "so": 41,
    "wp": 0,
    "balk": 0,
    "runs": 9,
    "er": 7,
    "whip": 1.27
  },
  "asOf": "2026-07-06",
  "fetchedAt": "2026-07-07T04:39:47Z",
  "source": "NPB.jp 日本野球機構",
  "sourceUrl": "https://npb.jp/bis/2026/stats/pit_c.html"
}