{
  "slug": "maeda-kenta",
  "name": "前田 健太",
  "nameRomaji": "Maeda Kenta",
  "teamAbbr": "楽",
  "teamSlug": "rakuten-eagles",
  "teamName": "東北楽天ゴールデンイーグルス",
  "league": "pacific",
  "group": "pitching",
  "qualified": false,
  "season": "2026",
  "rank": null,
  "stats": {
    "era": 3.52,
    "games": 7,
    "wins": 1,
    "losses": 3,
    "saves": 0,
    "holds": 0,
    "hp": 0,
    "cg": 0,
    "sho": 0,
    "nbb": 0,
    "winpct": 0.25,
    "bf": 129,
    "ip": 30.2,
    "hits": 29,
    "hr": 3,
    "bb": 13,
    "ibb": 0,
    "hbp": 0,
    "so": 26,
    "wp": 0,
    "balk": 0,
    "runs": 12,
    "er": 12,
    "whip": 1.37
  },
  "asOf": "2026-07-02",
  "fetchedAt": "2026-07-03T04:33:18Z",
  "source": "NPB.jp 日本野球機構",
  "sourceUrl": "https://npb.jp/bis/2026/stats/idp1_e.html"
}