{
  "slug": "maruteinesu",
  "name": "マルティネス",
  "nameRomaji": "Maruteinesu",
  "teamAbbr": "巨",
  "teamSlug": "yomiuri-giants",
  "teamName": "読売ジャイアンツ",
  "league": "central",
  "group": "pitching",
  "qualified": false,
  "season": "2026",
  "rank": 1,
  "stats": {
    "era": 2.08,
    "games": 18,
    "wins": 1,
    "losses": 1,
    "saves": 15,
    "holds": 1,
    "hp": 2,
    "cg": 0,
    "sho": 0,
    "nbb": 0,
    "winpct": 0.5,
    "bf": 64,
    "ip": 17.1,
    "hits": 9,
    "hr": 0,
    "bb": 4,
    "ibb": 0,
    "hbp": 0,
    "so": 21,
    "wp": 0,
    "balk": 0,
    "runs": 4,
    "er": 4,
    "whip": 0.75
  },
  "asOf": "2026-06-01",
  "fetchedAt": "2026-06-02T05:27:01Z",
  "source": "NPB.jp 日本野球機構",
  "sourceUrl": "https://npb.jp/bis/2026/stats/pit_c.html"
}