{
  "slug": "masayoshi-tanaka",
  "name": "田中 正義",
  "nameRomaji": "Masayoshi Tanaka",
  "teamAbbr": "日",
  "teamSlug": "nipponham-fighters",
  "teamName": "北海道日本ハムファイターズ",
  "league": "pacific",
  "group": "pitching",
  "qualified": false,
  "season": "2026",
  "rank": 4,
  "stats": {
    "era": 2.42,
    "games": 26,
    "wins": 1,
    "losses": 2,
    "saves": 0,
    "holds": 17,
    "hp": 18,
    "cg": 0,
    "sho": 0,
    "nbb": 0,
    "winpct": 0.333,
    "bf": 97,
    "ip": 26,
    "hits": 16,
    "hr": 1,
    "bb": 3,
    "ibb": 0,
    "hbp": 2,
    "so": 27,
    "wp": 0,
    "balk": 0,
    "runs": 7,
    "er": 7,
    "whip": 0.73
  },
  "asOf": "2026-07-02",
  "fetchedAt": "2026-07-02T18:23:17Z",
  "source": "NPB.jp 日本野球機構",
  "sourceUrl": "https://npb.jp/bis/2026/stats/pit_p.html"
}