{
  "slug": "mishou-nishikawa",
  "name": "西川 史礁",
  "nameRomaji": "Mishou Nishikawa",
  "teamAbbr": "ロ",
  "teamSlug": "lotte-marines",
  "teamName": "千葉ロッテマリーンズ",
  "league": "pacific",
  "group": "batting",
  "qualified": true,
  "season": "2026",
  "rank": 4,
  "stats": {
    "avg": 0.296,
    "games": 85,
    "pa": 369,
    "ab": 334,
    "runs": 40,
    "hits": 99,
    "doubles": 21,
    "triples": 1,
    "hr": 7,
    "tb": 143,
    "rbi": 39,
    "sb": 2,
    "cs": 2,
    "sac": 0,
    "sf": 0,
    "bb": 29,
    "ibb": 1,
    "hbp": 6,
    "so": 60,
    "gidp": 9,
    "slg": 0.428,
    "obp": 0.363,
    "ops": 0.791
  },
  "asOf": "2026-07-23",
  "fetchedAt": "2026-07-23T18:08:13Z",
  "source": "NPB.jp 日本野球機構",
  "sourceUrl": "https://npb.jp/bis/2026/stats/bat_p.html"
}