{
  "slug": "miyagi-taki-ta",
  "name": "宮城 滝太",
  "nameRomaji": "Miyagi Taki Ta",
  "teamAbbr": "デ",
  "teamSlug": "yokohama-dena",
  "teamName": "横浜DeNAベイスターズ",
  "league": "central",
  "group": "pitching",
  "qualified": false,
  "season": "2026",
  "rank": null,
  "stats": {
    "era": 2.22,
    "games": 25,
    "wins": 0,
    "losses": 1,
    "saves": 0,
    "holds": 3,
    "hp": 3,
    "cg": 0,
    "sho": 0,
    "nbb": 0,
    "winpct": 0.0,
    "bf": 98,
    "ip": 24.1,
    "hits": 21,
    "hr": 3,
    "bb": 4,
    "ibb": 1,
    "hbp": 1,
    "so": 25,
    "wp": 2,
    "balk": 0,
    "runs": 6,
    "er": 6,
    "whip": 1.03
  },
  "asOf": "2026-07-18",
  "fetchedAt": "2026-07-19T14:47:15Z",
  "source": "NPB.jp 日本野球機構",
  "sourceUrl": "https://npb.jp/bis/2026/stats/idp1_db.html"
}