{
  "slug": "nahara-norihiko",
  "name": "名原 典彦",
  "nameRomaji": "Nahara Norihiko",
  "teamAbbr": "広",
  "teamSlug": "hiroshima-carp",
  "teamName": "広島東洋カープ",
  "league": "central",
  "group": "batting",
  "qualified": false,
  "season": "2026",
  "rank": null,
  "stats": {
    "avg": 0.265,
    "games": 38,
    "pa": 174,
    "ab": 162,
    "runs": 22,
    "hits": 43,
    "doubles": 4,
    "triples": 3,
    "hr": 3,
    "tb": 62,
    "rbi": 12,
    "sb": 4,
    "cs": 3,
    "sac": 2,
    "sf": 1,
    "bb": 8,
    "ibb": 0,
    "hbp": 1,
    "so": 22,
    "gidp": 1,
    "slg": 0.383,
    "obp": 0.302,
    "ops": 0.685
  },
  "asOf": "2026-07-14",
  "fetchedAt": "2026-07-15T03:50:31Z",
  "source": "NPB.jp 日本野球機構",
  "sourceUrl": "https://npb.jp/bis/2026/stats/idb1_c.html"
}