{
  "slug": "nebin",
  "name": "ネビン",
  "nameRomaji": "Nebin",
  "teamAbbr": "西",
  "teamSlug": "seibu-lions",
  "teamName": "埼玉西武ライオンズ",
  "league": "pacific",
  "group": "batting",
  "qualified": false,
  "season": "2026",
  "rank": null,
  "stats": {
    "avg": 0.274,
    "games": 46,
    "pa": 191,
    "ab": 168,
    "runs": 22,
    "hits": 46,
    "doubles": 11,
    "triples": 0,
    "hr": 11,
    "tb": 90,
    "rbi": 30,
    "sb": 0,
    "cs": 1,
    "sac": 0,
    "sf": 6,
    "bb": 13,
    "ibb": 0,
    "hbp": 4,
    "so": 39,
    "gidp": 2,
    "slg": 0.536,
    "obp": 0.33,
    "ops": 0.866
  },
  "asOf": "2026-07-13",
  "fetchedAt": "2026-07-14T03:49:38Z",
  "source": "NPB.jp 日本野球機構",
  "sourceUrl": "https://npb.jp/bis/2026/stats/idb1_l.html"
}