{
  "slug": "oonishi-hiroki",
  "name": "大西 広樹",
  "nameRomaji": "Oonishi Hiroki",
  "teamAbbr": "ヤ",
  "teamSlug": "yakult-swallows",
  "teamName": "東京ヤクルトスワローズ",
  "league": "central",
  "group": "pitching",
  "qualified": false,
  "season": "2026",
  "rank": null,
  "stats": {
    "era": 11.25,
    "games": 6,
    "wins": 0,
    "losses": 0,
    "saves": 0,
    "holds": 2,
    "hp": 2,
    "cg": 0,
    "sho": 0,
    "nbb": 0,
    "winpct": 0.0,
    "bf": 21,
    "ip": 4,
    "hits": 8,
    "hr": 1,
    "bb": 1,
    "ibb": 0,
    "hbp": 0,
    "so": 1,
    "wp": 1,
    "balk": 0,
    "runs": 6,
    "er": 5,
    "whip": 2.25
  },
  "asOf": "2026-07-08",
  "fetchedAt": "2026-07-09T11:55:51Z",
  "source": "NPB.jp 日本野球機構",
  "sourceUrl": "https://npb.jp/bis/2026/stats/idp1_s.html"
}