{
  "slug": "sanchuu-ryou-makoto",
  "name": "山中 稜真",
  "nameRomaji": "Sanchuu Ryou Makoto",
  "teamAbbr": "オ",
  "teamSlug": "orix-buffaloes",
  "teamName": "オリックス・バファローズ",
  "league": "pacific",
  "group": "batting",
  "qualified": false,
  "season": "2026",
  "rank": null,
  "stats": {
    "avg": 0.319,
    "games": 37,
    "pa": 151,
    "ab": 135,
    "runs": 17,
    "hits": 43,
    "doubles": 7,
    "triples": 0,
    "hr": 0,
    "tb": 50,
    "rbi": 13,
    "sb": 2,
    "cs": 1,
    "sac": 0,
    "sf": 1,
    "bb": 14,
    "ibb": 0,
    "hbp": 1,
    "so": 22,
    "gidp": 4,
    "slg": 0.37,
    "obp": 0.384,
    "ops": 0.754
  },
  "asOf": "2026-07-10",
  "fetchedAt": "2026-07-11T14:44:09Z",
  "source": "NPB.jp 日本野球機構",
  "sourceUrl": "https://npb.jp/bis/2026/stats/idb1_b.html"
}