{
  "slug": "teruaki-sato",
  "name": "佐藤 輝明",
  "nameRomaji": "Teruaki Sato",
  "teamAbbr": "神",
  "teamSlug": "hanshin-tigers",
  "teamName": "阪神タイガース",
  "league": "central",
  "group": "batting",
  "qualified": true,
  "season": "2026",
  "rank": 1,
  "stats": {
    "avg": 0.34,
    "games": 79,
    "pa": 332,
    "ab": 288,
    "runs": 58,
    "hits": 98,
    "doubles": 25,
    "triples": 3,
    "hr": 18,
    "tb": 183,
    "rbi": 55,
    "sb": 5,
    "cs": 3,
    "sac": 0,
    "sf": 3,
    "bb": 41,
    "ibb": 5,
    "hbp": 0,
    "so": 83,
    "gidp": 4,
    "slg": 0.635,
    "obp": 0.419,
    "ops": 1.054
  },
  "asOf": "2026-07-12",
  "fetchedAt": "2026-07-13T16:21:32Z",
  "source": "NPB.jp 日本野球機構",
  "sourceUrl": "https://npb.jp/bis/2026/stats/bat_c.html"
}