{
  "slug": "tsumori-yuu-ki",
  "name": "津森 宥紀",
  "nameRomaji": "Tsumori Yuu Ki",
  "teamAbbr": "ソ",
  "teamSlug": "softbank-hawks",
  "teamName": "福岡ソフトバンクホークス",
  "league": "pacific",
  "group": "pitching",
  "qualified": false,
  "season": "2026",
  "rank": null,
  "stats": {
    "era": 1.59,
    "games": 25,
    "wins": 2,
    "losses": 0,
    "saves": 0,
    "holds": 5,
    "hp": 7,
    "cg": 0,
    "sho": 0,
    "nbb": 0,
    "winpct": 1.0,
    "bf": 84,
    "ip": 22.2,
    "hits": 9,
    "hr": 1,
    "bb": 7,
    "ibb": 1,
    "hbp": 2,
    "so": 18,
    "wp": 0,
    "balk": 0,
    "runs": 4,
    "er": 4,
    "whip": 0.71
  },
  "asOf": "2026-07-03",
  "fetchedAt": "2026-07-03T18:08:21Z",
  "source": "NPB.jp 日本野球機構",
  "sourceUrl": "https://npb.jp/bis/2026/stats/idp1_h.html"
}