{
  "slug": "yamazaki-fuku-ya",
  "name": "山﨑 福也",
  "nameRomaji": "Yamazaki Fuku Ya",
  "teamAbbr": "日",
  "teamSlug": "nipponham-fighters",
  "teamName": "北海道日本ハムファイターズ",
  "league": "pacific",
  "group": "pitching",
  "qualified": false,
  "season": "2026",
  "rank": null,
  "stats": {
    "era": 2.5,
    "games": 9,
    "wins": 1,
    "losses": 0,
    "saves": 0,
    "holds": 0,
    "hp": 0,
    "cg": 0,
    "sho": 0,
    "nbb": 0,
    "winpct": 1.0,
    "bf": 71,
    "ip": 18,
    "hits": 19,
    "hr": 1,
    "bb": 4,
    "ibb": 0,
    "hbp": 0,
    "so": 9,
    "wp": 0,
    "balk": 0,
    "runs": 5,
    "er": 5,
    "whip": 1.28
  },
  "asOf": "2026-07-06",
  "fetchedAt": "2026-07-07T04:39:47Z",
  "source": "NPB.jp 日本野球機構",
  "sourceUrl": "https://npb.jp/bis/2026/stats/idp1_f.html"
}