{
  "amazon_tag": "baseballab22-22",
  "links": [
    {
      "id": "sabr-intro",
      "label": "セイバーメトリクス入門 脱常識で野球を科学する",
      "url": "https://www.amazon.co.jp/dp/4880654779?tag=baseballab22-22",
      "icon": "📗",
      "bgColor": "#1b5e20",
      "imgUrl": "https://m.media-amazon.com/images/I/519rUSeuIYL.jpg",
      "pr": true,
      "description": "データで野球を読み解く思想と主要指標を、定説を疑う視点から体系的に解説。当サイトの「指標解説」をより深く理解したい人に最適な一冊。"
    },
    {
      "id": "sabr-fun",
      "label": "プロ野球・MLBが10倍楽しくなる！ よくわかるセイバーメトリクス",
      "url": "https://www.amazon.co.jp/dp/4768318029?tag=baseballab22-22",
      "icon": "📘",
      "bgColor": "#1a3a5c",
      "imgUrl": "https://m.media-amazon.com/images/I/51lStvg+NoL.jpg",
      "pr": true,
      "description": "大谷翔平らの実数値を題材に、OPS・WAR・FIPからトラッキングデータまで図解。数式が苦手なファンでも読み進められる入門書。"
    },
    {
      "id": "python-baseball",
      "label": "野球データでやさしく学べるPython入門",
      "url": "https://www.amazon.co.jp/dp/453406067X?tag=baseballab22-22",
      "icon": "🐍",
      "bgColor": "#2d6a4f",
      "imgUrl": "https://m.media-amazon.com/images/I/51EilUzMNvL.jpg",
      "pr": true,
      "description": "プロ野球・大谷翔平のデータを題材に、Pythonでのグラフ作成・分析を実践しながら習得。「読む」から「自分で分析する」へ進みたい人へ。"
    },
    {
      "id": "pocket-radar-jp",
      "label": "Pocket Radar ボールコーチ（スピードガン）",
      "url": "https://www.amazon.co.jp/dp/B00KGHXUZ4?tag=baseballab22-22",
      "icon": "📡",
      "bgColor": "#0f2540",
      "imgUrl": "https://m.media-amazon.com/images/I/41+v5H4-36L._AC_.jpg",
      "pr": true,
      "description": "手のひらサイズで球速・打球速度を±1mph精度で計測。指導者・プレーヤーが自分のデータを取りに行くための実機。"
    }
  ]
}
